anaximander/__init__.py
anaximander/dataobjects/__init__.py
anaximander/dataobjects/base.py
anaximander/dataobjects/collections.py
anaximander/dataobjects/columnar.py
anaximander/dataobjects/data.py
anaximander/dataobjects/models.py
anaximander/dataobjects/tabular.py
anaximander/descriptors/__init__.py
anaximander/descriptors/attributes.py
anaximander/descriptors/base.py
anaximander/descriptors/dataspec.py
anaximander/descriptors/datatypes.py
anaximander/descriptors/fields.py
anaximander/descriptors/fieldtypes.py
anaximander/descriptors/methods.py
anaximander/descriptors/schema.py
anaximander/descriptors/scope.py
anaximander/descriptors/typespec.py
anaximander/meta/__init__.py
anaximander/meta/arche.py
anaximander/meta/archetype.py
anaximander/meta/nxmeta.py
anaximander/meta/nxobject.py
anaximander/meta/nxtype.py
anaximander/meta/trait.py
anaximander/operators/__init__.py
anaximander/utilities/__init__.py
anaximander/utilities/functions.py
anaximander/utilities/nxdataclasses.py
anaximander/utilities/nxyaml.py
anaximander-0.4a1.dist-info/LICENSE
anaximander-0.4a1.dist-info/WHEEL
anaximander-0.4a1.dist-info/METADATA
anaximander-0.4a1.dist-info/RECORD
