Metadata-Version: 2.1
Name: anaximander
Version: 0.4a1
Summary: The rapid application development framework for data-intensive Python
Home-page: https://www.anaximander.dev
License: MPL-2.0
Author: Novavia Solutions
Author-email: info@novavia.us
Requires-Python: >=3.10,<4.0
Classifier: Development Status :: 3 - Alpha
Classifier: License :: OSI Approved
Classifier: License :: OSI Approved :: Mozilla Public License 2.0 (MPL 2.0)
Classifier: Operating System :: OS Independent
Classifier: Programming Language :: Python :: 3
Classifier: Programming Language :: Python :: 3.10
Requires-Dist: beartype (>=0.10.4,<0.11.0)
Requires-Dist: frozendict (>=2.3,<3.0)
Requires-Dist: pandas (>=1.4,<2.0)
Requires-Dist: petl (>=1.7.9,<2.0.0)
Requires-Dist: pydantic (>=1.9,<2.0)
Requires-Dist: python-dotenv (>=0.20.0,<0.21.0)
Requires-Dist: ruamel.yaml (>=0.17,<0.18)
Requires-Dist: sortedcontainers (>=2.4.0,<3.0.0)
Project-URL: Repository, https://github.com/novavia/anaximander
